kconvert/__init__.py
kconvert/kconvert.py
kconvert-0.1.2.dist-info/METADATA
kconvert-0.1.2.dist-info/WHEEL
kconvert-0.1.2.dist-info/entry_points.txt
kconvert-0.1.2.dist-info/RECORD
