Metadata-Version: 2.1
Name: kconvert
Version: 0.1.2
Summary: Binary to decimal and decimal to binary converter
Author: dongjin2008
Author-email: dkim@icsparis.fr
Requires-Python: >=3.10,<4.0
Classifier: Programming Language :: Python :: 3
Classifier: Programming Language :: Python :: 3.10
Classifier: Programming Language :: Python :: 3.11
